influxdb_cli/__init__.py
influxdb_cli/file_writer.py
influxdb_cli/helper.py
influxdb_cli/influx3.py
influxdb_cli/openai_helper.py
influxdb3_python_cli-0.3.2.dist-info/LICENSE
influxdb3_python_cli-0.3.2.dist-info/METADATA
influxdb3_python_cli-0.3.2.dist-info/WHEEL
influxdb3_python_cli-0.3.2.dist-info/entry_points.txt
influxdb3_python_cli-0.3.2.dist-info/top_level.txt
influxdb3_python_cli-0.3.2.dist-info/RECORD
