Metadata-Version: 2.1
Name: influxdb3-python-cli
Version: 0.3.2
Summary: Community Python client for InfluxDB 3.0 (CLI)
Home-page: https://github.com/InfluxCommunity/influxdb-python-cli
Author: InfluxData
Author-email: contact@influxdata.com
Classifier: Development Status :: 4 - Beta
Classifier: Intended Audience :: Developers
Classifier: License :: OSI Approved :: MIT License
Classifier: Programming Language :: Python :: 3
Classifier: Programming Language :: Python :: 3.6
Classifier: Programming Language :: Python :: 3.7
Classifier: Programming Language :: Python :: 3.8
Classifier: Programming Language :: Python :: 3.9
Classifier: Programming Language :: Python :: 3.10
License-File: LICENSE
Requires-Dist: influxdb3-python
Requires-Dist: pygments
Requires-Dist: prompt-toolkit
Requires-Dist: pandas
Requires-Dist: tabulate
Requires-Dist: openai
